cistercian.py
cistercian-1.0.1.dist-info/licenses/LICENSE
cistercian-1.0.1.dist-info/METADATA
cistercian-1.0.1.dist-info/WHEEL
cistercian-1.0.1.dist-info/top_level.txt
cistercian-1.0.1.dist-info/RECORD
