Metadata-Version: 2.4
Name: cistercian
Version: 1.0.1
Summary: A library for generating Cistercian Numeral images.
Home-page: https://github.com/teeale/Cistercian
Author: tealee
Author-email: tealej7@gmail.com
Keywords: numerals,cistercian,images
Classifier: Programming Language :: Python
Classifier: Programming Language :: Python :: 3
Classifier: Programming Language :: Python :: 3.6
Classifier: Programming Language :: Python :: 3.7
Classifier: Programming Language :: Python :: 3.8
Classifier: Programming Language :: Python :: 3.9
Classifier: Programming Language :: Python :: 3.10
Classifier: Programming Language :: Python :: Implementation :: CPython
Classifier: Intended Audience :: Developers
Classifier: License :: OSI Approved :: MIT License
Classifier: Operating System :: OS Independent
Classifier: Topic :: Text Processing :: Linguistic
Classifier: Topic :: Utilities
Classifier: Development Status :: 4 - Beta
Requires-Python: >=3.6
License-File: LICENSE
Requires-Dist: Pillow>=8.0.0
Dynamic: license-file
